odoo/addons/account_billing/README.rst
odoo/addons/account_billing/__init__.py
odoo/addons/account_billing/__manifest__.py
odoo/addons/account_billing/data/account_billing_sequence.xml
odoo/addons/account_billing/data/server_action.xml
odoo/addons/account_billing/i18n/account_billing.pot
odoo/addons/account_billing/i18n/es.po
odoo/addons/account_billing/i18n/fr_FR.po
odoo/addons/account_billing/i18n/it.po
odoo/addons/account_billing/i18n/nl_NL.po
odoo/addons/account_billing/i18n/zh_CN.po
odoo/addons/account_billing/models/__init__.py
odoo/addons/account_billing/models/account_billing.py
odoo/addons/account_billing/models/account_move.py
odoo/addons/account_billing/readme/CONTRIBUTORS.md
odoo/addons/account_billing/readme/DESCRIPTION.md
odoo/addons/account_billing/readme/USAGE.md
odoo/addons/account_billing/report/report.xml
odoo/addons/account_billing/report/report_billing.xml
odoo/addons/account_billing/security/account_billing_security.xml
odoo/addons/account_billing/security/ir.model.access.csv
odoo/addons/account_billing/static/description/icon.png
odoo/addons/account_billing/static/description/index.html
odoo/addons/account_billing/static/src/img/icon.png
odoo/addons/account_billing/tests/__init__.py
odoo/addons/account_billing/tests/test_account_billing.py
odoo/addons/account_billing/views/account_billing_views.xml
odoo/addons/account_billing/views/account_move_views.xml
odoo_addon_account_billing-18.0.1.1.0.dist-info/METADATA
odoo_addon_account_billing-18.0.1.1.0.dist-info/WHEEL
odoo_addon_account_billing-18.0.1.1.0.dist-info/top_level.txt
odoo_addon_account_billing-18.0.1.1.0.dist-info/RECORD
